_examples/__init__.py
examples/README.rst
examples/__init__.py
pd_utils/__init__.py
pd_utils/corr.py
pd_utils/cum.py
pd_utils/datetime_utils.py
pd_utils/filldata.py
pd_utils/load.py
pd_utils/merge.py
pd_utils/plot.py
pd_utils/port.py
pd_utils/query.py
pd_utils/regby.py
pd_utils/testing.py
pd_utils/timer.py
pd_utils/transform.py
pd_utils/utils.py
pd_utils/optimize/__init__.py
pd_utils/optimize/dftypes.py
pd_utils/optimize/typing.py
pd_utils/optimize/load/__init__.py
tests/__init__.py
tests/base.py
tests/test_pandas.py
tests/test_plot.py
tests/input_files/multi_axis_plot.png
tests/input_files/multi_axis_plot_axis_locations.png
tests/input_files/multi_axis_plot_axis_locations_colored.png
tests/input_files/multi_axis_plot_colored.png
pd_utils-0.2.3.dist-info/LICENSE.md
pd_utils-0.2.3.dist-info/METADATA
pd_utils-0.2.3.dist-info/WHEEL
pd_utils-0.2.3.dist-info/entry_points.txt
pd_utils-0.2.3.dist-info/top_level.txt
pd_utils-0.2.3.dist-info/RECORD
