Metadata-Version: 2.1
Name: pd-utils
Version: 0.2.3
Summary: High-level tools for common Pandas workflows
Home-page: https://github.com/nickderobertis/pd-utils
Author: Nick DeRobertis
Author-email: whoopnip@gmail.com
License: MIT
Project-URL: Code, https://github.com/nickderobertis/pd-utils
Project-URL: Documentation, https://nickderobertis.github.io/pd-utils
Platform: UNKNOWN
Classifier: Development Status :: 3 - Alpha
Classifier: Intended Audience :: Developers
Classifier: Programming Language :: Python :: 3.6
Classifier: Programming Language :: Python :: 3.7
License-File: LICENSE.md
Requires-Dist: pandas
Requires-Dist: numpy
Requires-Dist: pandasql
Requires-Dist: sas7bdat
Requires-Dist: statsmodels
Requires-Dist: matplotlib
